structlog_overtime/__init__.py
structlog_overtime/bind.py
structlog_overtime/filter.py
structlog_overtime/mock.py
structlog_overtime/noop.py
structlog_overtime/py.typed
structlog_overtime/tee.py
structlog_overtime/timestamper.py
structlog_overtime-1.0.1.dist-info/METADATA
structlog_overtime-1.0.1.dist-info/WHEEL
structlog_overtime-1.0.1.dist-info/top_level.txt
structlog_overtime-1.0.1.dist-info/RECORD
